banner_whitecapella/__init__.py
banner_whitecapella/banner.py
banner_whitecapella-0.3.9.dist-info/METADATA
banner_whitecapella-0.3.9.dist-info/WHEEL
banner_whitecapella-0.3.9.dist-info/entry_points.txt
banner_whitecapella-0.3.9.dist-info/top_level.txt
banner_whitecapella-0.3.9.dist-info/RECORD
