Metadata-Version: 2.1
Name: banner_whitecapella
Version: 0.3.9
Author-email: Whitecapella1 <whitecapella@naver.com>
License: MIT
Project-URL: Homepage, https://github.com/WhiteCapella/banner_whitecapella
Project-URL: Issues, https://github.com/WhiteCapella/banner_whitecapella/issues
Requires-Python: >=3.8
Requires-Dist: pyfiglet >=1.0.2
